LICENSE
MANIFEST.in
README.md
setup.py
./requirements.txt
./setups/api/requirements.txt
./setups/gui/requirements.txt
./setups/web/requirements.txt
kot/__init__.py
kot.egg-info/PKG-INFO
kot.egg-info/SOURCES.txt
kot.egg-info/dependency_links.txt
kot.egg-info/entry_points.txt
kot.egg-info/not-zip-safe
kot.egg-info/requires.txt
kot.egg-info/top_level.txt
kot/core/__init__.py
kot/core/kot.py
kot/core/serial.py
kot/interfaces/api.py
kot/interfaces/gui_web.py
kot/remote/__init__.py
kot/remote/controller.py
kot/remote/helper.py
kot/remote/interface.py