Metadata-Version: 2.1
Name: kot
Version: 0.42.2
Summary: Flexible, secure and scalable database and your python cloud.
Home-page: https://github.com/KOT-database/KOT
Author: Onur Atakan ULUSOY
Author-email: atadogan06@gmail.com
License: MIT
Platform: UNKNOWN
Requires-Python: >= 3
